{
  "metadata": {
    "generatedAt": "2026-07-04T14:13:16.105Z",
    "phase": 8,
    "milestone": "M2",
    "track": "V3-multi-class-ensemble",
    "symbol": "SOL/USDT",
    "ltfTimeframe": "1h",
    "timeframe": "1d",
    "initialEquityUsd": 10000
  },
  "config": {
    "leverage": 10,
    "volTarget": 0.02,
    "entryPctl": 0.75,
    "exitPctl": 0.5,
    "windowDays": 30,
    "cooldownHours": 72,
    "baseNotionalUsd": 10000,
    "maxDailyVarPct": 0.02,
    "varConfidence": 0.95
  },
  "result": {
    "trades": 117,
    "totalPnlUsd": -523.5665154621056,
    "totalReturnPct": -5.235665154621056,
    "maxDrawdownPct": 6.083152007711896,
    "sharpeRatio": -0.9012909855358842,
    "winRate": 0.3504273504273504,
    "totalTrades": 117,
    "killSwitchTriggered": false
  },
  "tradesByReason": {
    "take_profit": 41,
    "stop_loss": 75,
    "time_exit": 1
  },
  "volTargetedSizer": {
    "config": {
      "windowDays": 30,
      "targetDailyVol": 0.02,
      "minVolMultiplier": 0.25,
      "maxVolMultiplier": 1,
      "annualizationFactor": 19.1049731745428,
      "minRealizedVolFloor": 0.0001
    },
    "avgMultiplier": 0.5210493711581845,
    "avgRealizedDailyVol": 0.0411907943331493,
    "avgRealizedAnnualizedVol": 0.7869490207729263,
    "lowerClampFraction": 0,
    "upperClampFraction": 0.003278688524590164,
    "middleFraction": 0.9967213114754099,
    "totalDays": 915,
    "recommendedMaxPositionPctEquity": 0.10420987423163691
  },
  "ensembleState": {
    "donchianSignalsEmitted": 117,
    "donchianTimeExitCloses": 0,
    "fundingCarryUsd": 12318.12499999998,
    "fundingCarryTimeInCarryFraction": 0.9684123430351407,
    "fundingCarryEntries": 1,
    "effectiveCarryLeverage": 5,
    "volTargetedAvgMultiplier": 0.5514282150231821,
    "dailyVaR95Pct": 0,
    "liquidationEvents": 0,
    "combinedEdgePct": 0,
    "carrySide": {
      "fundingCollectedUsd": 0,
      "rebalanceCount": 0,
      "rebalanceCostUsd": 0,
      "lastMarkPrice": 82.91,
      "unrealizedDeltaUsd": 0,
      "hasEntered": true,
      "currentLeverage": 1,
      "effectiveNotionalUsd": 10000,
      "initialMarginUsd": 10000,
      "maintenanceMarginUsd": 50,
      "dailyVaR95Pct": 0,
      "liquidationEventsCount": 0,
      "fundingHistory": [],
      "lastFundingRates": []
    },
    "timingSide": {
      "fundingHistory": [
        0.00006335,
        0.0000748,
        0.00003702,
        0.00004292,
        0.000023,
        0.00003645,
        0.00002671,
        0.00005009,
        -0.00002566,
        0.00003141,
        0.0001,
        0.00002624,
        -0.0000438,
        -0.00019668,
        -0.00004817,
        -0.00004446,
        -0.00012086,
        -0.00018206,
        -0.00006287,
        -0.00009673,
        -0.00025721,
        -0.00008011,
        -0.0000732,
        -0.00018542,
        -0.00016398,
        -0.0000723,
        -0.00023704,
        -0.00038757,
        -0.00025513,
        -0.00022946,
        -0.00001174,
        -0.00006393,
        -0.00002354,
        -0.00009828,
        0.0000179,
        -0.00008438,
        -0.00001777,
        -0.00008243,
        -0.00000825,
        -0.00000336,
        -0.00009068,
        -0.00009448,
        -0.00002866,
        -0.00005235,
        -0.00002582,
        -0.00000455,
        -0.00012137,
        -0.00010682,
        -0.00009337,
        -0.00003596,
        -0.00003856,
        -0.00004542,
        0.00001871,
        -0.00001544,
        -0.00002499,
        -0.0000017,
        -0.00005638,
        -0.00003481,
        -0.00005509,
        -0.00004124,
        -0.0000267,
        0.0001,
        0.00006065,
        -0.00003617,
        -0.00003087,
        -0.00003337,
        -0.00001391,
        0.00004438,
        0.00002277,
        0.00000745,
        0.00004338,
        -0.00004305,
        -0.00003017,
        -0.00002964,
        -0.00009607,
        -0.00020855,
        -0.00008775,
        -0.00007233,
        -0.00001309,
        -0.00011854,
        -0.00004028,
        -0.00004827,
        0.00003113,
        0.00008442,
        0.00006096,
        0.0001,
        0.0000481,
        -0.0000193,
        0.0000163,
        0.00002764,
        0.00000968,
        0.00000521,
        0.00003745,
        0.00004184,
        0.0001,
        0.00007704,
        0.00007228,
        0.0001
      ],
      "isInCarry": true,
      "lastEntryTimeMs": 1706659200000,
      "lastExitTimeMs": null,
      "entryCount": 1,
      "exitCount": 0,
      "fundingCollectedUsd": 12318.12499999998,
      "inCarryFundingPeriods": 2737,
      "outOfCarryFundingPeriods": 0,
      "negativeFundingPaidUsd": -7223.568000000008,
      "lastMarkPrice": 82.91,
      "hasEntered": true,
      "lastStats": {
        "count": 98,
        "median": -0.00002768,
        "mean": -0.000035029183673469405,
        "stdDev": 0.00008821515915352293,
        "min": -0.00038757,
        "max": 0.0001,
        "p25": -0.00007298250000000001,
        "p75": 0.0000265925,
        "p90": 0.00006167699999999999
      }
    },
    "recommendedMaxPositionPctEquity": 0.10420987423163691
  },
  "carryContribution": {
    "fundingCollectedUsd": 12318.12499999998,
    "fundingSnapshotsApplied": 2737,
    "fundingSnapshotsSkipped": 0,
    "effectiveCarryLeverage": 5,
    "avgFundingRate8h": 7.552246230354634e-7
  },
  "combinedEdge": {
    "totalPnlUsd": 11794.558484537874,
    "directionalPnlUsd": -523.5665154621056,
    "carryPnlUsd": 12318.12499999998,
    "totalReturnPct": 117.94558484537873,
    "monthlyReturnPct": 3.9315194948459578,
    "sharpe": -14.307550839793576,
    "maxDrawdownPct": 6.083152007711896,
    "annualizedReturnPct": 47.17823393815149,
    "carryComponentPct": 104.43905141636694
  },
  "volTargetSeries": {
    "firstFew": [
      {
        "day": 1704067200000,
        "realizedDailyVol": 0,
        "clampedVolMultiplier": 1
      },
      {
        "day": 1704153600000,
        "realizedDailyVol": 0,
        "clampedVolMultiplier": 1
      },
      {
        "day": 1704240000000,
        "realizedDailyVol": 0.03583839164542679,
        "clampedVolMultiplier": 0.5580607578005563
      },
      {
        "day": 1704326400000,
        "realizedDailyVol": 0.07244140731329367,
        "clampedVolMultiplier": 0.2760851941142482
      },
      {
        "day": 1704412800000,
        "realizedDailyVol": 0.061408242490770745,
        "clampedVolMultiplier": 0.3256891776866252
      }
    ],
    "lastFew": [
      {
        "day": 1782691200000,
        "realizedDailyVol": 0.038501103208441925,
        "clampedVolMultiplier": 0.5194656343149853
      },
      {
        "day": 1782777600000,
        "realizedDailyVol": 0.0386235587756635,
        "clampedVolMultiplier": 0.5178186742491967
      },
      {
        "day": 1782864000000,
        "realizedDailyVol": 0.0397933726089861,
        "clampedVolMultiplier": 0.5025962538164865
      },
      {
        "day": 1782950400000,
        "realizedDailyVol": 0.036785357150005,
        "clampedVolMultiplier": 0.5436945988710424
      },
      {
        "day": 1783036800000,
        "realizedDailyVol": 0.03626945349388624,
        "clampedVolMultiplier": 0.5514282150231821
      }
    ]
  }
}